{
  "configVersion": 1,
  "timestamp": 1599918831426,
  "index": "/index.html",
  "assetGroups": [
    {
      "name": "app",
      "installMode": "prefetch",
      "updateMode": "prefetch",
      "cacheQueryOptions": {
        "ignoreVary": true
      },
      "urls": [
        "/4.29256c6fb6388cbccb0c.js",
        "/favicon.ico",
        "/index.html",
        "/main.e24c693edd663a15c0b7.js",
        "/manifest.webmanifest",
        "/polyfills.a4021de53358bb0fec14.js",
        "/runtime.5e9bf5a8d7d50eeb334e.js",
        "/styles.e8fffac43904fa235480.css"
      ],
      "patterns": []
    },
    {
      "name": "assets",
      "installMode": "lazy",
      "updateMode": "prefetch",
      "cacheQueryOptions": {
        "ignoreVary": true
      },
      "urls": [
        "/assets/fonts/msuighub.ttf",
        "/assets/fonts/msuighur.ttf",
        "/assets/icons/icon-128x128.png",
        "/assets/icons/icon-144x144.png",
        "/assets/icons/icon-152x152.png",
        "/assets/icons/icon-192x192.png",
        "/assets/icons/icon-384x384.png",
        "/assets/icons/icon-512x512.png",
        "/assets/icons/icon-72x72.png",
        "/assets/icons/icon-96x96.png",
        "/assets/img/phaarmaicon-horizental.png",
        "/assets/img/phaarmaicon-textless.png",
        "/assets/img/phaarmaicon.png"
      ],
      "patterns": []
    }
  ],
  "dataGroups": [],
  "hashTable": {
    "/4.29256c6fb6388cbccb0c.js": "c679f06ee3bbb5fa31f5cd634b0b805db54827d4",
    "/assets/fonts/msuighub.ttf": "cc8d631452580680e3795964fec81270ccd45d9c",
    "/assets/fonts/msuighur.ttf": "6618b004395c7e11f92d2cdf505f04e7d5713029",
    "/assets/icons/icon-128x128.png": "f02c97a2958d2f8506556d489b30a117a6a9d841",
    "/assets/icons/icon-144x144.png": "f02c97a2958d2f8506556d489b30a117a6a9d841",
    "/assets/icons/icon-152x152.png": "f02c97a2958d2f8506556d489b30a117a6a9d841",
    "/assets/icons/icon-192x192.png": "f02c97a2958d2f8506556d489b30a117a6a9d841",
    "/assets/icons/icon-384x384.png": "f02c97a2958d2f8506556d489b30a117a6a9d841",
    "/assets/icons/icon-512x512.png": "f02c97a2958d2f8506556d489b30a117a6a9d841",
    "/assets/icons/icon-72x72.png": "f02c97a2958d2f8506556d489b30a117a6a9d841",
    "/assets/icons/icon-96x96.png": "f02c97a2958d2f8506556d489b30a117a6a9d841",
    "/assets/img/phaarmaicon-horizental.png": "a74619fd5c4cf9ce318e3187f05ddadd49580726",
    "/assets/img/phaarmaicon-textless.png": "48d58db0f1c440ebcd1cae2533c0638921c6f1c5",
    "/assets/img/phaarmaicon.png": "37ab6e0517be0133a997a15725012fef99ce6ef5",
    "/favicon.ico": "22f6a4a3bcaafafb0254e0f2fa4ceb89e505e8b2",
    "/index.html": "3504bed549bc45b3709b3275fd8891a927fc3928",
    "/main.e24c693edd663a15c0b7.js": "d9877f4d24be38c01f2e6b6c8a85badd9a3ec2c9",
    "/manifest.webmanifest": "dd305b51b0b94d2d8a1c927becf6633c587cae0a",
    "/polyfills.a4021de53358bb0fec14.js": "b47435a9ef2a4829f2f9dfd35599bde3614981b1",
    "/runtime.5e9bf5a8d7d50eeb334e.js": "143fa7b1f9e7e654b87a19aeebc0296fdaa8195a",
    "/styles.e8fffac43904fa235480.css": "9aa2ef23cb3bd0d78e3be26d29f7cd302c195607"
  },
  "navigationUrls": [
    {
      "positive": true,
      "regex": "^\\/.*$"
    },
    {
      "positive": false,
      "regex": "^\\/(?:.+\\/)?[^/]*\\.[^/]*$"
    },
    {
      "positive": false,
      "regex": "^\\/(?:.+\\/)?[^/]*__[^/]*$"
    },
    {
      "positive": false,
      "regex": "^\\/(?:.+\\/)?[^/]*__[^/]*\\/.*$"
    }
  ]
}